__init__.py
cloudflare_ips_reload.py
cloudflare_only_nginx-1.0.0.dist-info/LICENSE
cloudflare_only_nginx-1.0.0.dist-info/METADATA
cloudflare_only_nginx-1.0.0.dist-info/WHEEL
cloudflare_only_nginx-1.0.0.dist-info/entry_points.txt
cloudflare_only_nginx-1.0.0.dist-info/top_level.txt
cloudflare_only_nginx-1.0.0.dist-info/RECORD
