Metadata-Version: 2.1
Name: cloudflare-only-nginx
Version: 1.0.0
Summary: nginx-style network configuration
Author-email: c0m4r <github@wolfet.pl>
License: MIT
Project-URL: Homepage, https://github.com/c0m4r/cloudflare-only-nginx
Project-URL: Issues, https://github.com/c0m4r/cloudflare-only-nginx/issues
Keywords: cloudflare,nginx
Classifier: Programming Language :: Python :: 3
Classifier: License :: OSI Approved :: MIT License
Classifier: Operating System :: OS Independent
Requires-Python: >=3.8
License-File: LICENSE
Requires-Dist: requests >=2.31.0
